moat/lib/priomap/__init__.py
moat/lib/priomap/_impl.py
moat_lib_priomap-0.2.3.dist-info/licenses/LICENSE
moat_lib_priomap-0.2.3.dist-info/licenses/LICENSE.txt
moat_lib_priomap-0.2.3.dist-info/METADATA
moat_lib_priomap-0.2.3.dist-info/WHEEL
moat_lib_priomap-0.2.3.dist-info/top_level.txt
moat_lib_priomap-0.2.3.dist-info/RECORD
